{
	"Items" : [
		{"Tags": ["Rich", "Average", "Poor"], "Description": "piece of chalk"},
		{"Tags": ["Rich", "Average", "Poor"], "Description": "shopping list"},
		{"Tags": ["Rich", "Average", "Poor"], "Description": "hankerchief"},
		{"Tags": ["Rich", "Average", "Poor"], "Description": "{Cost} deck of cards"},
		{"Tags": ["Rich", "Average", "Poor"], "Description": "piece of a broken sword"},
		{"Tags": ["Rich", "Average", "Poor"], "Description": "blood stained hankerchief"},
		{"Tags": ["Rich", "Average", "Poor", "Food"], "Description": "bag of walnuts"},
		{"Tags": ["Rich", "Average", "Poor"], "Description": "hastily drawn map with an x over a nearby landmark"},
		{"Tags": ["Rich", "Average", "Poor", "Alcohol"], "Description": "{Size} pouch of pipeweed"},{"Tags": ["Rich", "Average", "Poor", "Alcohol"], "Description": "{Material} smoking pipe"},
		{"Tags": ["Rich", "Average", "Poor"], "Description": "polished rock"},
		{"Tags": ["Rich", "Average", "Poor"], "Description": "ancient knuckle bone"},
		{"Tags": ["Rich", "Average", "Poor"], "Description": "{Quality} throwing dice"},
		{"Tags": ["Rich", "Average", "Poor"], "Description": "{Material} throwing dice"},
		{"Tags": ["Rich", "Average", "Poor"], "Description": "{Leather} gloves"},
		{"Tags": ["Rich", "Average", "Poor"], "Description": "{Quality} {Leather} bracelet"},
		{"Tags": ["Rich", "Average", "Poor", "Alcohol"], "Description": "bottle of {AlcoholQuality} brandy"},
		{"Tags": ["Rich", "Average", "Poor", "Alcohol"], "Description": "bottle of {AlcoholQuality} beer"},
		{"Tags": ["Rich", "Average", "Poor", "Alcohol"], "Description": "bottle of {AlcoholQuality} wine"},
		{"Tags": ["Average", "Poor"], "Description": "{Size} bag of {BagContents}"},
		{"Tags": ["Average", "Poor"], "Description": "{Size} jar of {Contents}"},
		{"Tags": ["Rich", "Average"], "Description": "{Size} vial of {Contents}"},
		{"Tags": ["Average", "Poor", "Food"], "Description": "strip of {FoodQuality} jerky"},
		{"Tags": ["Average", "Poor", "Food"], "Description": "piece of {FoodQuality} bread"},
		{"Tags": ["Average", "Poor", "Food"], "Description": "loaf of {FoodQuality} bread"},
		{"Tags": ["Average", "Rich", "Food"], "Description": "loaf of artisanel bread"},
		{"Tags": ["Average", "Poor", "Food"], "Description": "{FoodQuality} bread roll"},
		{"Tags": ["Poor"], "Description": "pouch of seeds"},
		{"Tags": ["Poor", "Food"], "Description": "wedge of {FoodQuality} cheese"},
		{"Tags": ["Poor", "Food"], "Description": "{Size} pouch of dried berries"},
		{"Tags": ["Poor", "Food"], "Description": "handfull of dried mushrooms"},
		{"Tags": ["Average", "Poor"], "Description": "piece of charcoal"},
		{"Tags": ["Poor"], "Description": "piece of charcoal"},
		{"Tags": ["Average", "Food"], "Description": "{Leather} bag of jerky"},
		{"Tags": ["Average"], "Description": "map of the district"},
		{"Tags": ["Average", "Food"], "Description": "small Leather-wrapped wheel of cheese"},
		{"Tags": ["Average", "Poor"], "Description": "rabbits foot"},
		{"Tags": ["Average", "Poor"], "Description": "spool of thread and needle"},
		{"Tags": ["Average", "Rich"], "Description": "{Quality} set of artists brushes"},
		{"Tags": ["Rich", "Average"], "Description": "{Cost} quill"},
		{"Tags": ["Rich", "Average"], "Description": "{Cost} inkwell"},
		{"Tags": ["Rich", "Average"], "Description": "map of the city"},
		{"Tags": ["Rich", "Food"], "Description": "aromatic paper-wrapped cheese"},
		{"Tags": ["Rich", "Average"], "Description": "{Size} empty glass vial"},
		{"Tags": ["Rich", "Average"], "Description": "{Threat} {From} a {Person}"},
		{"Tags": ["Rich"], "Description": "papers of lineage"},
		{"Tags": ["Rich", "Average"], "Description": "{Quality} {Leather} folio of local plants"},
		{"Tags": ["Rich", "Average"], "Description": "{Material} signet ring"},
		{"Tags": ["Rich"], "Description": "sheet of terrible poetry"},
		{"Tags": ["Rich"], "Description": "{Quality} book"},
		{"Tags": ["Rich", "Arcane", "Average"], "Description": "a copy of \"%BookName%\""},
		{"Tags": ["Rich"], "Description": "{Quality} book"},
		{"Tags": ["Rich"], "Description": "{Size} {Quality} book"},
		{"Tags": ["Rich", "Average"], "Description": "{Size} {Quality} journal"},
		{"Tags": ["Rich"], "Description": "{Quality} fountainpen"},
		{"Tags": ["Rich"], "Description": "{Quality} {Material} comb"},
		{"Tags": ["Rich"], "Description": "{Size} {Quality} {Material} comb"},
		{"Tags": ["Rich"], "Description": "{Material} religious symbol"},
		{"Tags": ["Rich"], "Description": "{Size} {Quality} {Material} religious symbol"},
		{"Tags": ["Rich"], "Description": "{Quality} bell"},
		{"Tags": ["Rich"], "Description": "{Size} {Quality} bell"},
		{"Tags": ["Rich", "Average"], "Description": "pincushion"},
		{"Tags": ["Rich", "Average", "Poor"], "Description": "needle case"},
		{"Tags": ["Rich", "Average"], "Description": "thimble"},
		{"Tags": ["Rich", "Average", "Poor"], "Description": "short measuring string"},
		{"Tags": ["Rich"], "Description": "{Material} key"},
		{"Tags": ["Rich"], "Description": "{Size} {Material} key"},
		{"Tags": ["Rich"], "Description": "{Size} {Material} coin"},
		{"Tags": ["Poor", "Average"], "Description": "{Size} {Material} statue of a local folk hero"},
		{"Tags": ["Rich", "Average"], "Description": "{Size} {Color} key, not legal tender"},
		{"Tags": ["Rich"], "Description": "{Material} cipher ring"},
		{"Tags": ["Rich"], "Description": "{Size} leather-bound cipher book"},
		{"Tags": ["Rich"], "Description": "short coded document"},
		{"Tags": ["Rich", "Average"], "Description": "{Quality} merchants weights"},
		{"Tags": ["Rich"], "Description": "{Size} set of {Quality} merchants weights"},
		{"Tags": ["Rich"], "Description": "{Jewelry}"},
		{"Tags": ["Rich"], "Description": "{Size} {Material} mirror"},
		{"Tags": ["Rich"], "Description": "{Jewelry}"},
		{"Tags": ["Rich", "Average"], "Description": "{Jewelry}"},
		{"Tags": ["Rich", "Average", "Poor"], "Description": "{Jewelry}"},
		{"Tags": ["Arcane"], "Description": "a {size} glass bottle with {ArcaneThing} trapped inside"},
		{"Tags": ["Arcane"], "Description": "a gaunt, severed, hand that coninues to move on it's own."},
		{"Tags": ["Rich", "Average", "Poor"], "Description": "{Instrument}"},
		{"Tags": ["Rich", "Average", "Poor"], "Description": "{Size} {Material} marble"},
		{"Tags": ["Average", "Poor"], "Description": "{Size} box of seeds"},
		{"Tags": ["Rich", "Average", "Poor"], "Description": "{Jewelry}"},
		{"Tags": ["Rich", "Average", "Poor"], "Description": "{Jewelry}"},
		{"Tags": ["Rich", "Average", "Poor"], "Description": "{Jewelry}"}
	],
	"Jewelry" : [
		{"Tags": ["Rich", "Average", "Poor"], "Description": "{Size} {Material} icon"},
		{"Tags": ["Rich", "Average", "Poor"], "Description": "{Size} {Material} cameo brooch"},
		{"Tags": ["Rich", "Average", "Poor"], "Description": "{Size} {Material} necklace"},
		{"Tags": ["Rich", "Average", "Poor"], "Description": "{Size} {Material} bracelet"},
		{"Tags": ["Rich", "Average", "Poor"], "Description": "{Size} {Material} earrings"}
	],
	"ArcaneThing" : [
		{"Tags": ["Rich", "Average", "Poor"], "Description": "a {color} light"},
		{"Tags": ["Rich", "Average", "Poor"], "Description": "a lighting bolt"},
		{"Tags": ["Rich", "Average", "Poor"], "Description": "a ghostly {Animal}"}
	],
	"Instrument" : [
		{"Tags": ["Rich"], "Description": "bandore"},
		{"Tags": ["Rich", "Average"], "Description": "lute"},
		{"Tags": ["Rich", "Average"], "Description": "fiddle"},
		{"Tags": ["Poor"], "Description": "drum"},
		{"Tags": ["Poor"], "Description": "whistle"}
	],"Material" : [
		{"Tags": ["Rich"], "Description": "gold"},
		{"Tags": ["Rich", "Average"], "Description": "silver"},
		{"Tags": ["Rich"], "Description": "crystal"},
		{"Tags": ["Rich"], "Description": "ebony"},
		{"Tags": ["Rich"], "Description": "ivory"},
		{"Tags": ["Rich"], "Description": "onyx"},
		{"Tags": ["Average"], "Description": "yew"},
		{"Tags": ["Average"], "Description": "brass"},
		{"Tags": ["Average"], "Description": "bronze"},
		{"Tags": ["Average"], "Description": "stone"},
		{"Tags": ["Poor"], "Description": "antler"},
		{"Tags": ["Poor"], "Description": "bone"},
		{"Tags": ["Poor"], "Description": "oak"},
		{"Tags": ["Poor"], "Description": "copper"},
		{"Tags": ["Poor"], "Description": "tin"}
	],
	"Quality" : [
		{"Tags": ["Rich", "Average"], "Description": "finely crafted"},
		{"Tags": ["Rich"], "Description": "bejewelled"},
		{"Tags": ["Rich"], "Description": "ornate"},
		{"Tags": ["Average"], "Description": "well made"},
		{"Tags": ["Rich", "Average", "Poor"], "Description": "sturdy"},
		{"Tags": ["Average"], "Description": "decorative"},
		{"Tags": ["Poor"], "Description": "shoddy"},
		{"Tags": ["Poor"], "Description": "well worn"},
		{"Tags": ["Poor", "Average"], "Description": "worn out"},
		{"Tags": ["Poor"], "Description": "rough"}
	],
	"Person" : [
		{"Tags": ["Rich", "Average"], "Description": "local merchant"},
		{"Tags": ["Rich", "Average"], "Description": "local noble"},
		{"Tags": ["Rich", "Average"], "Description": "unknown person"},
		{"Tags": ["Rich", "Average"], "Description": "foreign noble"},
		{"Tags": ["Rich", "Average"], "Description": "foreign dignitary"},
		{"Tags": ["Poor", "Average"], "Description": "local farmer"},
		{"Tags": ["Poor", "Average"], "Description": "local serf"}
	],
	"Threat" : [
		{"Tags": ["Rich", "Average"], "Description": "death threat"},
		{"Tags": ["Average", "Poor"], "Description": "eviction threat"},
		{"Tags": ["Rich", "Average", "Poor"], "Description": "threat"}
	],
	"From" : [
		{"Tags": ["Rich", "Average", "Poor"], "Description": "from"},
		{"Tags": ["Rich", "Average", "Poor"], "Description": "against"}
	],
	"Size" : [
		{"Tags": ["Rich", "Average", "Poor"], "Description": "small"},
		{"Tags": ["Rich", "Average", "Poor"], "Description": "large"},
		{"Tags": ["Rich", "Average", "Poor"], "Description": "tiny"}
	],
	"Leather" : [
		{"Tags": ["Rich", "Average", "Poor"], "Description": "leather"},
		{"Tags": ["Rich", "Average"], "Description": "supple leather"},
		{"Tags": ["Rich", "Average"], "Description": "dark leather"},
		{"Tags": ["Rich", "Average", "Poor"], "Description": "light leather"},
		{"Tags": ["Average", "Poor"], "Description": "rough leather"}
	],
	"Contents" : [
		{"Tags": ["Rich", "Average", "Poor"], "Description": "ashes"},
		{"Tags": ["Rich", "Average", "Poor"], "Description": "herbs"},
		{"Tags": ["Rich", "Average", "Poor"], "Description": "salt"},
		{"Tags": ["Rich", "Average", "Poor"], "Description": "honey"},
		{"Tags": ["Rich", "Average", "Poor"], "Description": "ointment"},
		{"Tags": ["Rich", "Average", "Poor"], "Description": "sand"},
		{"Tags": ["Rich", "Average"], "Description": "{Color} liquid"},
		{"Tags": ["Average", "Poor"], "Description": "dirt"}
	],
	"BagContents" : [
		{"Tags": ["Rich", "Average", "Poor"], "Description": "herbs"},
		{"Tags": ["Rich", "Average", "Poor"], "Description": "salt"},
		{"Tags": ["Rich", "Average", "Poor"], "Description": "walnuts"},
		{"Tags": ["Average", "Poor"], "Description": "rocks"},
		{"Tags": ["Rich", "Average", "Poor"], "Description": "pipeweed"},
		{"Tags": ["Average", "Poor"], "Description": "dried mushrooms"},
		{"Tags": ["Average", "Poor"], "Description": "sand"}
	],
	"Color" : [
		{"Tags": ["Rich", "Average", "Poor"], "Description": "puple"},
		{"Tags": ["Rich", "Average", "Poor"], "Description": "brown"},
		{"Tags": ["Rich", "Average", "Poor"], "Description": "rich golden"},
		{"Tags": ["Rich", "Average", "Poor"], "Description": "teal"},
		{"Tags": ["Rich", "Average", "Poor"], "Description": "blue"},
		{"Tags": ["Rich", "Average", "Poor"], "Description": "green"},
		{"Tags": ["Rich", "Average", "Poor"], "Description": "reddish"},
		{"Tags": ["Rich", "Average", "Poor"], "Description": "burgundy"}
	],
	"Cost" : [
		{"Tags": ["Average", "Poor"], "Description": "cheap"},
		{"Tags": ["Rich"], "Description": "extravagant"},
		{"Tags": ["Rich", "Average"], "Description": "expensive"},
		{"Tags": ["Rich", "Average", "Poor"], "Description": ""}
	],
	"Animal" : [
		{"Tags": [], "Description": "bat"},
		{"Tags": [], "Description": "cat"},
		{"Tags": [], "Description": "wolf"},
		{"Tags": [], "Description": "bear"},
		{"Tags": [], "Description": "hawk"},
		{"Tags": [], "Description": "hydra"},
		{"Tags": [], "Description": "skeleton"},
		{"Tags": [], "Description": "dragon"}
	],
	"FoodQuality" : [
		{"Tags": ["Average", "Poor"], "Description": "dry"},
		{"Tags": ["Average", "Poor", "Rich"], "Description": "good"},
		{"Tags": ["Poor"], "Description": "moldy"},
		{"Tags": ["Poor"], "Description": "old"},
		{"Tags": ["Rich", "Average"], "Description": "excellent"},
		{"Tags": ["Rich"], "Description": "artisanel"}
	],
	"AlcoholQuality" : [
		{"Tags": ["Average", "Poor"], "Description": "cheap"},
		{"Tags": ["Average", "Poor"], "Description": "harsh"},
		{"Tags": ["Poor"], "Description": "terrible"},
		{"Tags": ["Average", "Rich"], "Description": "good"},
		{"Tags": ["Rich", "Average"], "Description": "excellent"},
		{"Tags": ["Rich", "Average"], "Description": "rich"},
		{"Tags": ["Rich"], "Description": "suberb"},
		{"Tags": ["Rich"], "Description": "aged"}
	]
}